{
  "kind": "spec_vs_diff_report",
  "version": "1.0",
  "generatedAt": "2026-02-10T04:12:39.533Z",
  "summary": "GalleryPage.tsx was updated to reference 12 uploaded image filenames under `/assets/gallery/` with descriptive English `alt` and `title` fields, replacing the previous placeholder path usage. However, the diff shows no new static image assets added, so the uploaded files’ inclusion as frontend assets cannot be verified from this change set.",
  "missing_requirements": [
    {
      "id": "REQ-12",
      "requirement": "Add the 12 uploaded image files as static frontend assets so they load correctly in production builds.",
      "reason": "The diff summary shows no added files, and only code changes referencing `/assets/gallery/...`. Without the actual image files being added to the repo under the expected static assets directory, production builds may not include them.",
      "evidence": [
        "File diff summary: \"Added: 0\"",
        "frontend/src/pages/GalleryPage.tsx (references `/assets/gallery/*.jpg` but no corresponding assets are shown as added)"
      ]
    }
  ],
  "hallucinated_features": [],
  "confidence": 0.72,
  "changed_files": [
    "frontend-file-summaries.txt",
    "frontend/src/pages/GalleryPage.tsx",
    "project_state.json"
  ]
}